ioctl/__init__.py
ioctl/hidraw.py
ioctl-0.2.2.dist-info/LICENSE
ioctl-0.2.2.dist-info/METADATA
ioctl-0.2.2.dist-info/WHEEL
ioctl-0.2.2.dist-info/top_level.txt
ioctl-0.2.2.dist-info/RECORD
