Metadata-Version: 2.1
Name: ioctl
Version: 0.2.2
Summary: UNKNOWN
Home-page: https://github.com/FFY00/python-ioctl
Author: Filipe Laíns
Author-email: lains@archlinux.org
License: MIT
Platform: UNKNOWN
Classifier: License :: OSI Approved :: MIT License
Classifier: Programming Language :: Python :: 3.6
Classifier: Programming Language :: Python :: 3.7
Classifier: Programming Language :: Python :: 3.8
Classifier: Programming Language :: Python :: 3.9
Classifier: Programming Language :: Python :: 3.10
Classifier: Topic :: System :: Operating System Kernels :: Linux
Requires-Python: <4,>=3.6
License-File: LICENSE
